{"chunk_definitions":[{"chunk_id":"cyot4m48ectmq","chunk_label":"unnamed-chunk-1","document_id":"24E292FD","expansion_state":0,"options":{"engine":"r","label":"unnamed-chunk-181"},"row":16,"row_count":1,"visible":true},{"chunk_id":"cuq5elm1h5odo","chunk_label":"unnamed-chunk-2","document_id":"24E292FD","expansion_state":0,"options":{"engine":"r","label":"unnamed-chunk-238","message":false},"row":27,"row_count":1,"visible":true},{"chunk_id":"cvp3y0ou70f36","chunk_label":"unnamed-chunk-3","document_id":"24E292FD","expansion_state":0,"options":{"engine":"r","label":"unnamed-chunk-183"},"row":33,"row_count":1,"visible":true},{"chunk_id":"c41eomnspop6x","chunk_label":"unnamed-chunk-4","document_id":"24E292FD","expansion_state":0,"options":{"engine":"r","label":"unnamed-chunk-185"},"row":45,"row_count":1,"visible":true},{"chunk_id":"c0vqqy4w00dc7","chunk_label":"unnamed-chunk-7","document_id":"24E292FD","expansion_state":0,"options":{"engine":"r","label":"unnamed-chunk-231"},"row":79,"row_count":1,"visible":true},{"chunk_id":"cq5omveec8fpi","chunk_label":"unnamed-chunk-10","document_id":"24E292FD","expansion_state":0,"options":{"engine":"r","label":"unnamed-chunk-389","message":false},"row":102,"row_count":1,"visible":true}],"doc_write_time":1511510926}